{
  "version": "0.3.3",
  "flags": {},
  "shapes": [
    {
      "label": "STRUT_RAIL",
      "text": "",
      "points": [
        [
          449.1,
          284.9
        ],
        [
          455.7,
          294.8
        ],
        [
          487.5,
          311.5
        ],
        [
          491.2,
          311.3
        ],
        [
          496.3,
          311.9
        ],
        [
          499.8,
          315.8
        ],
        [
          503.2,
          323.1
        ],
        [
          501.9,
          328.0
        ],
        [
          498.2,
          330.7
        ],
        [
          491.3,
          329.8
        ],
        [
          479.5,
          334.5
        ],
        [
          596.3265306122448,
          340.0
        ],
        [
          603.469387755102,
          332.65306122448976
        ],
        [
          597.1428571428571,
          322.0408163265306
        ],
        [
          588.7755102040816,
          301.4285714285714
        ],
        [
          595.3061224489795,
          291.4285714285714
        ],
        [
          592.4489795918367,
          290.204081632653
        ]
      ],
      "bbox": [],
      "object_class_label_id": 262144,
      "group_id": null,
      "shape_type": "polygon",
      "flags": {}
    },
    {
      "label": "PURLIN",
      "text": "",
      "points": [
        [
          230.67331670822944,
          116.6583541147132
        ],
        [
          238.40399002493766,
          116.6583541147132
        ],
        [
          240.89775561097258,
          121.89526184538653
        ],
        [
          246.63341645885288,
          122.39401496259352
        ],
        [
          251.6209476309227,
          115.91022443890273
        ],
        [
          262.3441396508728,
          116.6583541147132
        ],
        [
          302.4,
          278.3
        ],
        [
          282.1,
          277.4
        ],
        [
          240.35256410256414,
          152.8846153846154
        ]
      ],
      "bbox": [],
      "object_class_label_id": 786432,
      "group_id": null,
      "shape_type": "polygon",
      "flags": {}
    },
    {
      "label": "PURLIN",
      "text": "",
      "points": [
        [
          1.2807881773399714,
          168.91625615763547
        ],
        [
          95.67873303167424,
          269.00452488687785
        ],
        [
          66.8390804597701,
          267.4329501915709
        ],
        [
          0,
          199
        ]
      ],
      "bbox": [],
      "object_class_label_id": 786432,
      "group_id": null,
      "shape_type": "polygon",
      "flags": {}
    },
    {
      "label": "STRUT_RAIL",
      "text": "",
      "points": [
        [
          424.88317757009344,
          284.2056074766355
        ],
        [
          302.1,
          278.3
        ],
        [
          282.1,
          277.5
        ],
        [
          271.1290322580645,
          277.9032258064516
        ],
        [
          263.7096774193548,
          305.0
        ],
        [
          260.1612903225806,
          304.35483870967744
        ],
        [
          266.61290322580646,
          277.9032258064516
        ],
        [
          94.93368700265255,
          268.83289124668437
        ],
        [
          66.55172413793106,
          267.50663129973475
        ],
        [
          0,
          264
        ],
        [
          0.0,
          302.0
        ],
        [
          409.78234582829504,
          329.7460701330109
        ],
        [
          402.1644498186215,
          324.30471584038696
        ],
        [
          392.00725513905684,
          323.8210399032648
        ],
        [
          388.3796856106409,
          318.01692865779927
        ],
        [
          384.7521160822249,
          317.2914147521161
        ],
        [
          384.51027811366384,
          312.93833131801694
        ],
        [
          388.5006045949214,
          312.4546553808948
        ],
        [
          390.55622732769046,
          308.2224909310762
        ],
        [
          394.3047158403869,
          306.4087061668682
        ],
        [
          402.64812575574365,
          306.52962515114876
        ],
        [
          424.53446191051995,
          296.37243047158404
        ]
      ],
      "bbox": [],
      "object_class_label_id": 262144,
      "group_id": null,
      "shape_type": "polygon",
      "flags": {}
    },
    {
      "label": "SOLAR_PANEL",
      "text": "",
      "points": [
        [
          245.08474576271186,
          91.86440677966101
        ],
        [
          251.6949152542373,
          115.59322033898304
        ],
        [
          247.0,
          122.2
        ],
        [
          240.7,
          121.8
        ],
        [
          238.5,
          116.8
        ],
        [
          230.4,
          116.4
        ],
        [
          243.841059602649,
          164.40397350993376
        ],
        [
          275.5,
          258.4
        ],
        [
          272.2,
          261.0
        ],
        [
          271.3,
          267.5
        ],
        [
          266.4,
          268.7
        ],
        [
          260.0,
          267.2
        ],
        [
          257.8,
          268.3
        ],
        [
          262.2,
          272.9
        ],
        [
          255.7,
          273.0
        ],
        [
          258.2,
          277.4
        ],
        [
          95.10961214165262,
          268.95446880269816
        ],
        [
          1.224489795918367,
          168.77551020408166
        ],
        [
          0.0,
          103.46938775510206
        ],
        [
          184.10579345088163,
          93.95465994962215
        ]
      ],
      "bbox": [],
      "object_class_label_id": 589824,
      "group_id": null,
      "shape_type": "polygon",
      "flags": {}
    }
  ],
  "imagePath": "1731529947_586285056.png",
  "imageData": null,
  "imageHeight": 360,
  "imageWidth": 640,
  "labelFilePath": "../image_segmentation_label/1731529947_586285056_label.tif"
}